moside6-0.1.0.dist-info/METADATA
moside6-0.1.0.dist-info/WHEEL
moside6-0.1.0.dist-info/entry_points.txt
moside6-0.1.0.dist-info/licenses/LICENSE
moside6/__init__.py
moside6/assets/__init__.py
moside6/assets/i18n/modern_main_window_en_US.qm
moside6/assets/i18n/modern_main_window_en_US.ts
moside6/assets/i18n/modern_main_window_zh_CN.qm
moside6/assets/i18n/modern_main_window_zh_CN.ts
moside6/assets/resources.py
moside6/assets/resources.qrc
moside6/assets/themes/dracula/icons/cil-3d.png
moside6/assets/themes/dracula/icons/cil-4k.png
moside6/assets/themes/dracula/icons/cil-account-logout.png
moside6/assets/themes/dracula/icons/cil-action-redo.png
moside6/assets/themes/dracula/icons/cil-action-undo.png
moside6/assets/themes/dracula/icons/cil-airplane-mode-off.png
moside6/assets/themes/dracula/icons/cil-airplane-mode.png
moside6/assets/themes/dracula/icons/cil-alarm.png
moside6/assets/themes/dracula/icons/cil-align-center.png
moside6/assets/themes/dracula/icons/cil-align-left.png
moside6/assets/themes/dracula/icons/cil-align-right.png
moside6/assets/themes/dracula/icons/cil-arrow-bottom-2.png
moside6/assets/themes/dracula/icons/cil-arrow-bottom.png
moside6/assets/themes/dracula/icons/cil-arrow-circle-bottom.png
moside6/assets/themes/dracula/icons/cil-arrow-circle-left.png
moside6/assets/themes/dracula/icons/cil-arrow-circle-right.png
moside6/assets/themes/dracula/icons/cil-arrow-circle-top.png
moside6/assets/themes/dracula/icons/cil-arrow-left.png
moside6/assets/themes/dracula/icons/cil-arrow-right.png
moside6/assets/themes/dracula/icons/cil-arrow-top.png
moside6/assets/themes/dracula/icons/cil-at.png
moside6/assets/themes/dracula/icons/cil-av-timer.png
moside6/assets/themes/dracula/icons/cil-ban.png
moside6/assets/themes/dracula/icons/cil-battery-0.png
moside6/assets/themes/dracula/icons/cil-battery-3.png
moside6/assets/themes/dracula/icons/cil-battery-5.png
moside6/assets/themes/dracula/icons/cil-battery-alert.png
moside6/assets/themes/dracula/icons/cil-battery-slash.png
moside6/assets/themes/dracula/icons/cil-bell.png
moside6/assets/themes/dracula/icons/cil-bluetooth.png
moside6-0.1.0.dist-info/RECORD
